trpl_m-2.2.0.dist-info/licenses/LICENSE
trplm/__init__.py
trplm/__main__.py
trplm/trpl_m.py
trpl_m-2.2.0.dist-info/METADATA
trpl_m-2.2.0.dist-info/WHEEL
trpl_m-2.2.0.dist-info/entry_points.txt
trpl_m-2.2.0.dist-info/top_level.txt
trpl_m-2.2.0.dist-info/RECORD
